[
  {
    "id": "de-heise-news",
    "name": "Heise Online News",
    "url": "https://www.heise.de/rss/heise-atom.xml",
    "category": "german-news",
    "enabled": true,
    "maxArticles": 20
  },
  {
    "id": "de-golem",
    "name": "Golem.de",
    "url": "https://rss.golem.de/rss.php?feed=ATOM1.0",
    "category": "german-tech",
    "enabled": true,
    "maxArticles": 20
  },
  {
    "id": "de-t3n",
    "name": "t3n Magazin",
    "url": "https://t3n.de/rss.xml",
    "category": "german-tech",
    "enabled": true,
    "maxArticles": 20
  },
  {
    "id": "de-handelsblatt",
    "name": "Handelsblatt Digital",
    "url": "https://www.handelsblatt.com/contentexport/feed/themen/digitalisierung",
    "category": "german-business",
    "enabled": true,
    "maxArticles": 15
  },
  {
    "id": "de-spiegel-tech",
    "name": "Spiegel Netzwelt",
    "url": "https://www.spiegel.de/netzwelt/index.rss",
    "category": "german-tech",
    "enabled": true,
    "maxArticles": 15
  },
  {
    "id": "de-chip",
    "name": "CHIP Online",
    "url": "https://www.chip.de/rss/rss_topnews.xml",
    "category": "german-tech",
    "enabled": true,
    "maxArticles": 15
  },
  {
    "id": "de-computerwoche",
    "name": "Computerwoche",
    "url": "https://www.computerwoche.de/feeds/rss-feed",
    "category": "german-tech",
    "enabled": true,
    "maxArticles": 15
  },
  {
    "id": "de-manager-magazin",
    "name": "Manager Magazin Digital",
    "url": "https://www.manager-magazin.de/themen/digitalisierung/index.rss",
    "category": "german-business",
    "enabled": true,
    "maxArticles": 10
  }
]